precompute/__init__.py
precompute/offload.py
precompute-0.0.1.dist-info/METADATA
precompute-0.0.1.dist-info/WHEEL
precompute-0.0.1.dist-info/top_level.txt
precompute-0.0.1.dist-info/RECORD
